sugar4/__init__.py
sugar4/__main__.py
sugar4/config.py
sugar4/debug.py
sugar4/env.py
sugar4/logger.py
sugar4/mime.py
sugar4/network.py
sugar4/profile.py
sugar4/util.py
sugar4/activity/__init__.py
sugar4/activity/activity.py
sugar4/activity/activityhandle.py
sugar4/activity/activityinstance.py
sugar4/activity/bundlebuilder.py
sugar4/activity/widgets.py
sugar4/bundle/__init__.py
sugar4/bundle/activitybundle.py
sugar4/bundle/bundle.py
sugar4/bundle/bundleversion.py
sugar4/bundle/contentbundle.py
sugar4/bundle/helpers.py
sugar4/datastore/__init__.py
sugar4/datastore/datastore.py
sugar4/dispatch/__init__.py
sugar4/dispatch/dispatcher.py
sugar4/dispatch/saferef.py
sugar4/graphics/__init__.py
sugar4/graphics/alert.py
sugar4/graphics/animator.py
sugar4/graphics/colorbutton.py
sugar4/graphics/combobox.py
sugar4/graphics/icon.py
sugar4/graphics/menuitem.py
sugar4/graphics/objectchooser.py
sugar4/graphics/palette.py
sugar4/graphics/palettegroup.py
sugar4/graphics/palettemenu.py
sugar4/graphics/palettewindow.py
sugar4/graphics/radiopalette.py
sugar4/graphics/radiotoolbutton.py
sugar4/graphics/style.py
sugar4/graphics/toggletoolbutton.py
sugar4/graphics/toolbarbox.py
sugar4/graphics/toolbox.py
sugar4/graphics/toolbutton.py
sugar4/graphics/toolcombobox.py
sugar4/graphics/tray.py
sugar4/graphics/window.py
sugar4/graphics/xocolor.py
sugar4/presence/__init__.py
sugar4/presence/activity.py
sugar4/presence/buddy.py
sugar4/presence/connectionmanager.py
sugar4/presence/presenceservice.py
sugar4/presence/sugartubeconn.py
sugar4/presence/tubeconn.py
sugar_toolkit_gtk4-1.1.4.dist-info/licenses/AUTHORS
sugar_toolkit_gtk4-1.1.4.dist-info/licenses/COPYING
sugar_toolkit_gtk4-1.1.4.dist-info/METADATA
sugar_toolkit_gtk4-1.1.4.dist-info/WHEEL
sugar_toolkit_gtk4-1.1.4.dist-info/entry_points.txt
sugar_toolkit_gtk4-1.1.4.dist-info/top_level.txt
sugar_toolkit_gtk4-1.1.4.dist-info/RECORD
