Metadata-Version: 2.4
Name: sugar-toolkit-gtk4
Version: 1.1.4
Summary: A GTK4 port of the Sugar Toolkit for Python activities
Author-email: Sugar Labs Community <sugar-devel@lists.sugarlabs.org>
License: LGPL-2.1-or-later
Project-URL: Homepage, https://github.com/sugarlabs/sugar-toolkit-gtk4
Project-URL: Repository, https://github.com/sugarlabs/sugar-toolkit-gtk4.git
Project-URL: Issues, https://github.com/sugarlabs/sugar-toolkit-gtk4/issues
Classifier: Development Status :: 3 - Alpha
Classifier: Intended Audience :: Developers
Classifier: Intended Audience :: Education
Classifier: Operating System :: POSIX :: Linux
Classifier: Programming Language :: Python :: 3
Classifier: Programming Language :: Python :: 3.8
Classifier: Programming Language :: Python :: 3.9
Classifier: Programming Language :: Python :: 3.10
Classifier: Programming Language :: Python :: 3.11
Classifier: Programming Language :: Python :: 3.12
Classifier: Topic :: Desktop Environment
Classifier: Topic :: Education
Classifier: Topic :: Software Development :: Libraries :: Python Modules
Classifier: Topic :: Software Development :: User Interfaces
Requires-Python: >=3.8
License-File: COPYING
License-File: AUTHORS
Requires-Dist: PyGObject>=3.42.0
Provides-Extra: dev
Requires-Dist: pytest>=6.0; extra == "dev"
Requires-Dist: pytest-cov; extra == "dev"
Requires-Dist: black; extra == "dev"
Requires-Dist: flake8; extra == "dev"
Requires-Dist: mypy; extra == "dev"
Requires-Dist: build; extra == "dev"
Requires-Dist: twine; extra == "dev"
Provides-Extra: test
Requires-Dist: pytest>=6.0; extra == "test"
Requires-Dist: pytest-cov; extra == "test"
Provides-Extra: docs
Requires-Dist: sphinx>=7.1.0; extra == "docs"
Requires-Dist: sphinx-rtd-theme>=1.3.0; extra == "docs"
Requires-Dist: sphinx-autoapi>=2.1.1; extra == "docs"
Requires-Dist: six>=1.16.0; extra == "docs"
Requires-Dist: decorator>=5.1.0; extra == "docs"
Dynamic: license-file
